wiggle_camera/__init__.py
wiggle_camera/camera.py
wiggle_camera/enhance.py
wiggle_camera/install.py
wiggle_camera/light.py
wiggle_camera/main.py
wiggle_camera/object_detection.py
wiggle_camera/timelapse.py
wiggle_camera/vision.py
wiggle_camera/write.py
wiggle_camera-0.0.4.dist-info/METADATA
wiggle_camera-0.0.4.dist-info/WHEEL
wiggle_camera-0.0.4.dist-info/entry_points.txt
wiggle_camera-0.0.4.dist-info/top_level.txt
wiggle_camera-0.0.4.dist-info/RECORD
