Metadata-Version: 2.1
Name: wiggle_camera
Version: 0.0.4
Summary: WiggleCamera - Control the camera on your WiggleBin
Author: Studio Rabota
Project-URL: Homepage, https://github.com/wiggle-bin/wiggle-camera.git
Classifier: Programming Language :: Python :: 3
Classifier: Operating System :: OS Independent
Requires-Python: >=3.7
Requires-Dist: pillow
Requires-Dist: adafruit-circuitpython-neopixel-spi
Requires-Dist: pandas
Requires-Dist: roboflow
